isdigit/__init__.py
isdigit/isdigit.py
IsDigit-0.0.10.dist-info/LICENSE
IsDigit-0.0.10.dist-info/METADATA
IsDigit-0.0.10.dist-info/WHEEL
IsDigit-0.0.10.dist-info/top_level.txt
IsDigit-0.0.10.dist-info/RECORD
