Metadata-Version: 2.1
Name: IsDigit
Version: 0.0.10
Summary: Simple, mainly useless, python package that checks if a string, int, or float is a digit.
Home-page: https://github.com/editid0/IsDigit
Author: editid
License: MIT
Keywords: python isdigit float int string
Platform: UNKNOWN
Classifier: Development Status :: 5 - Production/Stable
Classifier: Natural Language :: English
Classifier: Operating System :: OS Independent
Classifier: Programming Language :: Python :: 3.8
Classifier: Topic :: Software Development :: Libraries :: Python Modules
Classifier: Topic :: Utilities
Requires-Python: >=3.8.0
Provides-Extra: discord
Requires-Dist: discord.py ; extra == 'discord'
